{
  "name": "Mushrooms",
  "icon": "minecraft:brown_mushroom",
  "category": "world/plants",
  "advancement": "betterwithmods:crops/mushroom",
  "pages": [
    {
      "type": "crop",
      "name": "Mushrooms",
      "crop": "minecraft:brown_mushroom",
      "text": "A depiction of a wild mushroom."
    },
    {
      "type": "spotlight",
      "item": "minecraft:brown_mushroom",
      "title": "Seeds",
      "text": "Mushrooms are their own seeds. They seem to be found in dark and dank places such as caves and abandoned buildings. $(br2)Mushrooms seem to slowly spread when given enough darkness and time."
    },
    {
      "type": "spotlight",
      "item": "minecraft:brown_mushroom",
      "title": "Crop",
      "text": "Once harvested a mushroom can be processed in many different ways. The following pages are all the products I have been able to produce from mushrooms. "
    }
  ]
}
